pvpcheck/public_vs_private_pypi_check.py
pvpcheck-1.2.0.dist-info/METADATA
pvpcheck-1.2.0.dist-info/WHEEL
pvpcheck-1.2.0.dist-info/top_level.txt
pvpcheck-1.2.0.dist-info/RECORD
